gj_kingstar_api/__init__.py
gj_kingstar_api/demo.py
gj_kingstar_api/kingstar_client.py
gj_kingstar_api/market_listener.py
gj_kingstar_api/entity/__init__.py
gj_kingstar_api/entity/gtick.py
gj_kingstar_api/proto/__init__.py
gj_kingstar_api/proto/common_pb2.py
gj_kingstar_api/proto/common_pb2.pyi
gj_kingstar_api/proto/market_pb2.py
gj_kingstar_api/proto/market_pb2.pyi
gj_kingstar_api-1.0.3.dist-info/LICENSE
gj_kingstar_api-1.0.3.dist-info/METADATA
gj_kingstar_api-1.0.3.dist-info/WHEEL
gj_kingstar_api-1.0.3.dist-info/top_level.txt
gj_kingstar_api-1.0.3.dist-info/RECORD
