Metadata-Version: 2.2
Name: gj_kingstar_api
Version: 1.0.3
Summary: 金仕达行情封装
Author: diy
Author-email: 471293853@qq.com
Requires-Python: >3.6
License-File: LICENSE
Requires-Dist: protobuf>=4.24.4
Requires-Dist: websockets>=11.0.3
Dynamic: author
Dynamic: author-email
Dynamic: description
Dynamic: description-content-type
Dynamic: requires-dist
Dynamic: requires-python
Dynamic: summary
